odoo8_addon_l10n_it_ddt_delivery-8.0.1.0.0-py2.7-nspkg.pth
odoo_addons/l10n_it_ddt_delivery/__openerp__.py
odoo_addons/l10n_it_ddt_delivery/__init__.py
odoo_addons/l10n_it_ddt_delivery/README.rst
odoo_addons/l10n_it_ddt_delivery/models/sale_order.py
odoo_addons/l10n_it_ddt_delivery/models/__init__.py
odoo_addons/l10n_it_ddt_delivery/i18n/it.po
odoo_addons/l10n_it_ddt_delivery/wizards/__init__.py
odoo_addons/l10n_it_ddt_delivery/wizards/ddt_from_pickings.py
odoo_addons/l10n_it_ddt_delivery/tests/test_ddt_delivery.py
odoo_addons/l10n_it_ddt_delivery/tests/__init__.py
odoo_addons/l10n_it_ddt_delivery/static/description/icon.png
odoo8_addon_l10n_it_ddt_delivery-8.0.1.0.0.dist-info/top_level.txt
odoo8_addon_l10n_it_ddt_delivery-8.0.1.0.0.dist-info/WHEEL
odoo8_addon_l10n_it_ddt_delivery-8.0.1.0.0.dist-info/RECORD
odoo8_addon_l10n_it_ddt_delivery-8.0.1.0.0.dist-info/metadata.json
odoo8_addon_l10n_it_ddt_delivery-8.0.1.0.0.dist-info/DESCRIPTION.rst
odoo8_addon_l10n_it_ddt_delivery-8.0.1.0.0.dist-info/METADATA
odoo8_addon_l10n_it_ddt_delivery-8.0.1.0.0.dist-info/namespace_packages.txt
